{
"ItemList":[],
"FileName":"savedata_1",
"DefaultTeam":[["hero1","hero2","hero3","hero4"],[],[]],
"CurrentTeamData":[{"state":{"after":[],"always":[],"before":[]},"teamPos":1,"def":4,"atk":2,"team_index":1,"act":2,"shield":0,"hp":12},{"state":{"after":[],"always":[],"before":[]},"teamPos":2,"def":0,"atk":6,"team_index":2,"act":3,"shield":0,"hp":11},{"state":{"after":[],"always":[],"before":[]},"teamPos":3,"def":0,"atk":5,"team_index":3,"act":5,"shield":0,"hp":10},{"state":{"after":[],"always":[],"before":[]},"teamPos":4,"def":3,"atk":1,"team_index":4,"act":4,"shield":0,"hp":12}],
"CurrentTeam":["hero1","hero2","hero3","hero4"],
"CurrentScene":1,
"MapData":{"sceneList":[{"name":1,"events":{"ranSeed":1661844551,"event":["blackSmith"],"door":[],"story":[],"isBattle":true}}],"dropItem":1,"passedRoom":0,"stepFromDoor":1,"money":0},
"Backpack":[],
"CurrentDeafault":1
}